segal/__init__.py
segal/datasets/__init__.py
segal/datasets/base_dataset.py
segal/datasets/camvid.py
segal/datasets/cityscapes.py
segal/datasets/pascal_voc.py
segal/strategies/__init__.py
segal/strategies/ceal_sampling.py
segal/strategies/entropy_sampling.py
segal/strategies/least_confidence.py
segal/strategies/margin_sampling.py
segal/strategies/random_sampling.py
segal/strategies/strategy.py
segal/strategies/vote_sampling.py
segal/utils.py
segal-0.1.4.dist-info/LICENSE
segal-0.1.4.dist-info/WHEEL
segal-0.1.4.dist-info/METADATA
segal-0.1.4.dist-info/RECORD
